zuper_testint.cpython-38-darwin.so
zuper_testint.pyi
zuper_testint_z7-7.3.2202211922.dist-info/METADATA
zuper_testint_z7-7.3.2202211922.dist-info/WHEEL
zuper_testint_z7-7.3.2202211922.dist-info/entry_points.txt
zuper_testint_z7-7.3.2202211922.dist-info/top_level.txt
zuper_testint_z7-7.3.2202211922.dist-info/zip-safe
zuper_testint_z7-7.3.2202211922.dist-info/RECORD
